BlastML/__init__.py
BlastML/blastml.py
BlastML-0.2.9.dist-info/LICENSE
BlastML-0.2.9.dist-info/METADATA
BlastML-0.2.9.dist-info/WHEEL
BlastML-0.2.9.dist-info/top_level.txt
BlastML-0.2.9.dist-info/RECORD
