Metadata-Version: 2.1
Name: BlastML
Version: 0.2.9
Summary: BlastML is a Fast Machine Learning Prototyping Library
Home-page: https://github.com/shanytc/BlastML
Author: Shany Golan
Author-email: shanytc@gmail.com
License: UNKNOWN
Platform: UNKNOWN
Classifier: Programming Language :: Python :: 3
Classifier: License :: OSI Approved :: MIT License
Classifier: Operating System :: OS Independent
